LICENSE
README.md
setup.py
python_toolz/__init__.py
python_toolz/helper.py
python_toolz.egg-info/PKG-INFO
python_toolz.egg-info/SOURCES.txt
python_toolz.egg-info/dependency_links.txt
python_toolz.egg-info/requires.txt
python_toolz.egg-info/top_level.txt