Metadata-Version: 2.1
Name: python-toolz
Version: 0.1.6
Summary: Pyton helpers
Home-page: https://github.com/zguillez/python-toolz
Author: Guillermo de la Iglesia
Author-email: mail@zguillez.io
Classifier: Programming Language :: Python :: 3
Classifier: License :: OSI Approved :: MIT License
Classifier: Operating System :: OS Independent
License-File: LICENSE
